pyinfraformat/__init__.py
pyinfraformat/exceptions.py
pyinfraformat/core/__init__.py
pyinfraformat/core/coord_utils.py
pyinfraformat/core/core.py
pyinfraformat/core/io.py
pyinfraformat/core/utils.py
pyinfraformat/plots/__init__.py
pyinfraformat/plots/holes.py
pyinfraformat/plots/maps.py
pyinfraformat/plots/icons/FVT.svg
pyinfraformat/plots/icons/HE.svg
pyinfraformat/plots/icons/HE_DP.svg
pyinfraformat/plots/icons/HK.svg
pyinfraformat/plots/icons/HK_DP.svg
pyinfraformat/plots/icons/HP.svg
pyinfraformat/plots/icons/LY.svg
pyinfraformat/plots/icons/NE.svg
pyinfraformat/plots/icons/NO.svg
pyinfraformat/plots/icons/PA.svg
pyinfraformat/plots/icons/PA_WST.svg
pyinfraformat/plots/icons/PI.svg
pyinfraformat/plots/icons/PO.svg
pyinfraformat/plots/icons/PR.svg
pyinfraformat/plots/icons/PT.svg
pyinfraformat/plots/icons/SI.svg
pyinfraformat/plots/icons/SI_FVT.svg
pyinfraformat/plots/icons/TR.svg
pyinfraformat/plots/icons/VO.svg
pyinfraformat/plots/icons/VP.svg
pyinfraformat/plots/icons/WST.svg
pyinfraformat-25.7.10.dist-info/licenses/LICENSE
pyinfraformat-25.7.10.dist-info/METADATA
pyinfraformat-25.7.10.dist-info/WHEEL
pyinfraformat-25.7.10.dist-info/top_level.txt
pyinfraformat-25.7.10.dist-info/RECORD
