Metadata-Version: 2.4
Name: pyinfraformat
Version: 25.7.10
Summary: Python library for Finnish Infraformat
Author: Ari Hartikainen, Taavi Dettenborn, Martti Hallipelto
License: Apache-2.0
Keywords: infraformat
Classifier: Development Status :: 3 - Alpha
Classifier: Intended Audience :: Developers
Classifier: Topic :: Scientific/Engineering :: Physics
Classifier: License :: OSI Approved :: Apache Software License
Classifier: Programming Language :: Python :: 3
Classifier: Programming Language :: Python :: 3.6
Classifier: Programming Language :: Python :: 3.7
Classifier: Programming Language :: Python :: 3.8
License-File: LICENSE
Requires-Dist: chardet
Requires-Dist: folium
Requires-Dist: numpy
Requires-Dist: matplotlib
Requires-Dist: pandas
Requires-Dist: pyproj
Requires-Dist: xmltodict
Requires-Dist: owslib
Requires-Dist: requests
Requires-Dist: tqdm
Dynamic: author
Dynamic: classifier
Dynamic: description
Dynamic: description-content-type
Dynamic: keywords
Dynamic: license
Dynamic: license-file
Dynamic: requires-dist
Dynamic: summary
